processing/__init__.py
processing/combination.py
processing/transformation.py
utils/__init__.py
utils/io.py
utils/plot.py
image_processing_package_srmaia-0.0.1.dist-info/LICENSE
image_processing_package_srmaia-0.0.1.dist-info/METADATA
image_processing_package_srmaia-0.0.1.dist-info/WHEEL
image_processing_package_srmaia-0.0.1.dist-info/top_level.txt
image_processing_package_srmaia-0.0.1.dist-info/RECORD
