Metadata-Version: 2.1
Name: image-processing-package-srmaia
Version: 0.0.1
Summary: Pacote de processamento de imagens usando Skimage
Home-page: https://github.com/usrmaia/image-processing-package
Author: George Maia - usrmaia
Author-email: georgemaiaf@gmail.com
License: UNKNOWN
Platform: UNKNOWN
Requires-Python: >=3.8
License-File: LICENSE
Requires-Dist: matplotlib
Requires-Dist: numpy
Requires-Dist: scikit-image (>=0.16.1)
